{
  "version": "4.5.6",
  "flags": {},
  "shapes": [
    {
      "label": "square",
      "points": [
        [
          642.5682830810547,
          333.9999532699585
        ],
        [
          749.4714587737843,
          391.54334038054964
        ],
        [
          643.551797040169,
          467.6532769556025
        ],
        [
          538.0549682875264,
          384.7780126849894
        ]
      ],
      "group_id": null,
      "shape_type": "polygon",
      "flags": {}
    },
    {
      "label": "square",
      "points": [
        [
          1012.0,
          222.66666666666666
        ],
        [
          1098.2,
          241.0
        ],
        [
          1090.5,
          257.4
        ],
        [
          996.3,
          236.6
        ]
      ],
      "group_id": null,
      "shape_type": "polygon",
      "flags": {}
    }
  ],
  "imagePath": "20210506_GZ_shadow_cam2_147.jpg",
  "imageData": null,
  "imageHeight": 720,
  "imageWidth": 1280
}