{
  "version": "4.5.6",
  "flags": {},
  "shapes": [
    {
      "label": "square",
      "points": [
        [
          624.2995834350586,
          296.1262607574463
        ],
        [
          720.3879547119141,
          341.6064405441284
        ],
        [
          632.4538803100586,
          399.6148109436035
        ],
        [
          534.2454528808594,
          338.40620040893555
        ]
      ],
      "group_id": null,
      "shape_type": "polygon",
      "flags": {}
    },
    {
      "label": "square",
      "points": [
        [
          965.1234567901234,
          198.45679012345678
        ],
        [
          1043.9300411522634,
          213.58024691358023
        ],
        [
          1034.4650205761316,
          227.98353909465018
        ],
        [
          949.6913580246913,
          209.46502057613168
        ]
      ],
      "group_id": null,
      "shape_type": "polygon",
      "flags": {}
    }
  ],
  "imagePath": "20210506_GZ_shadow_cam0_31.jpg",
  "imageData": null,
  "imageHeight": 720,
  "imageWidth": 1280
}