{
  "version": "4.5.6",
  "flags": {},
  "shapes": [
    {
      "label": "square",
      "points": [
        [
          1053.2,
          236.2
        ],
        [
          1162.2,
          260.0
        ],
        [
          1167.2,
          284.4
        ],
        [
          1045.0,
          254.4
        ]
      ],
      "group_id": null,
      "shape_type": "polygon",
      "flags": {}
    }
  ],
  "imagePath": "20210506_GZ_shadow_cam0_105.jpg",
  "imageData": null,
  "imageHeight": 720,
  "imageWidth": 1280
}