{
  "version": "4.5.6",
  "flags": {},
  "shapes": [
    {
      "label": "square",
      "points": [
        [
          1105.1127819548872,
          256.69172932330827
        ],
        [
          1234.2857142857142,
          287.5187969924812
        ],
        [
          1250.2255639097743,
          320.7518796992481
        ],
        [
          1103.3082706766916,
          281.9548872180451
        ]
      ],
      "group_id": null,
      "shape_type": "polygon",
      "flags": {}
    }
  ],
  "imagePath": "20210506_GZ_shadow_cam0_141.jpg",
  "imageData": null,
  "imageHeight": 720,
  "imageWidth": 1280
}