{
  "version": "4.5.6",
  "flags": {},
  "shapes": [
    {
      "label": "square",
      "points": [
        [
          649.9313354492188,
          223.03627967834473
        ],
        [
          709.1628959276018,
          242.420814479638
        ],
        [
          651.8099547511313,
          262.66968325791856
        ],
        [
          592.6470588235294,
          238.68778280542986
        ]
      ],
      "group_id": null,
      "shape_type": "polygon",
      "flags": {}
    }
  ],
  "imagePath": "20210506_GZ_shadow_cam2_15.jpg",
  "imageData": null,
  "imageHeight": 720,
  "imageWidth": 1280
}