{
  "shapes": [
    {
      "shape_type": "polygon", 
      "points": [
        [
          697.1360381861574, 
          218.61575178997612
        ], 
        [
          766.1097852028639, 
          240.09546539379474
        ], 
        [
          708.1145584725537, 
          265.3937947494033
        ], 
        [
          638.6634844868735, 
          239.14081145584723
        ]
      ], 
      "flags": {}, 
      "group_id": null, 
      "label": "square"
    }, 
    {
      "shape_type": "polygon", 
      "points": [
        [
          405.4962921142578, 
          153.7070667743683
        ], 
        [
          425.891472868217, 
          162.015503875969
        ], 
        [
          369.4573643410853, 
          169.92248062015503
        ], 
        [
          352.09302325581393, 
          160.31007751937983
        ]
      ], 
      "flags": {}, 
      "group_id": null, 
      "label": "square"
    }
  ], 
  "imagePath": "20210506_GZ_normal_cam0_226.jpg", 
  "flags": {}, 
  "version": "4.5.5", 
  "imageData": null, 
  "imageWidth": 1280, 
  "imageHeight": 720
}