{
  "shapes": [
    {
      "shape_type": "polygon", 
      "points": [
        [
          227.86377708978327, 
          224.1486068111455
        ], 
        [
          240.55727554179566, 
          246.74922600619195
        ], 
        [
          108.6687306501548, 
          275.54179566563465
        ], 
        [
          109.90712074303406, 
          247.3684210526316
        ]
      ], 
      "flags": {}, 
      "group_id": null, 
      "label": "square"
    }
  ], 
  "imagePath": "20210506_GZ_normal_cam0_180.jpg", 
  "flags": {}, 
  "version": "4.5.5", 
  "imageData": null, 
  "imageWidth": 1280, 
  "imageHeight": 720
}