{
  "version": "4.5.6",
  "flags": {},
  "shapes": [
    {
      "label": "square",
      "points": [
        [
          1038.0306243896484,
          155.49538135528564
        ],
        [
          1128.2051282051282,
          169.37321937321937
        ],
        [
          1118.5185185185185,
          186.46723646723646
        ],
        [
          1020.2279202279202,
          170.65527065527064
        ]
      ],
      "group_id": null,
      "shape_type": "polygon",
      "flags": {}
    }
  ],
  "imagePath": "20210506_GZ_normal_cam2_30.jpg",
  "imageData": null,
  "imageHeight": 720,
  "imageWidth": 1280
}