{
  "version": "4.5.7",
  "flags": {},
  "shapes": [
    {
      "label": "square",
      "points": [
        [
          546.1397058823529,
          287.86764705882354
        ],
        [
          585.1102941176471,
          334.55882352941177
        ],
        [
          426.8630849220104,
          383.7088388214904
        ],
        [
          414.5580589254766,
          322.53032928942804
        ]
      ],
      "group_id": null,
      "shape_type": "polygon",
      "flags": {}
    }
  ],
  "imagePath": "20210618_GZ_slant_093039_35.jpg",
  "imageData": null,
  "imageHeight": 720,
  "imageWidth": 1280
}