{
  "version": "4.5.7",
  "flags": {},
  "shapes": [
    {
      "label": "square",
      "points": [
        [
          214.52892561983472,
          253.77685950413223
        ],
        [
          342.85714285714283,
          240.0
        ],
        [
          266.59504132231405,
          228.9834710743802
        ],
        [
          149.4,
          242.0
        ]
      ],
      "group_id": null,
      "shape_type": "polygon",
      "flags": {}
    }
  ],
  "imagePath": "20210618_GZ_slant_094115_628.jpg",
  "imageData": null,
  "imageHeight": 720,
  "imageWidth": 1280
}