{
  "version": "4.5.7",
  "flags": {},
  "shapes": [
    {
      "label": "square",
      "points": [
        [
          288.3851432800293,
          234.98303174972534
        ],
        [
          333.1807780320366,
          256.52173913043475
        ],
        [
          232.0366132723112,
          286.95652173913044
        ],
        [
          190.47992706298828,
          257.9179787635803
        ]
      ],
      "group_id": null,
      "shape_type": "polygon",
      "flags": {}
    }
  ],
  "imagePath": "20210622_GZ_030123828_46.jpg",
  "imageData": null,
  "imageHeight": 720,
  "imageWidth": 1280
}