{
  "version": "4.5.7",
  "flags": {},
  "shapes": [
    {
      "label": "square",
      "points": [
        [
          910.7,
          275.7
        ],
        [
          1057.815845824411,
          301.2847965738758
        ],
        [
          1105.6603773584905,
          349.895178197065
        ],
        [
          928.7211740041928,
          315.5136268343815
        ]
      ],
      "group_id": null,
      "shape_type": "polygon",
      "flags": {}
    },
    {
      "label": "square",
      "points": [
        [
          306.6450309753418,
          178.35906744003296
        ],
        [
          354.04930114746094,
          187.70002126693726
        ],
        [
          308.52487564086914,
          201.8360996246338
        ],
        [
          258.58646392822266,
          189.98820304870605
        ]
      ],
      "group_id": null,
      "shape_type": "polygon",
      "flags": {}
    }
  ],
  "imagePath": "20210622_GZ_027123459_48.jpg",
  "imageData": null,
  "imageHeight": 720,
  "imageWidth": 1280
}